ignorepy/__init__.py
ignorepy/__main__.py
ignorepy/genignore.py
ignorepy-0.1.0.dist-info/LICENSE
ignorepy-0.1.0.dist-info/METADATA
ignorepy-0.1.0.dist-info/WHEEL
ignorepy-0.1.0.dist-info/entry_points.txt
ignorepy-0.1.0.dist-info/top_level.txt
ignorepy-0.1.0.dist-info/RECORD
