Metadata-Version: 2.1
Name: ignorepy
Version: 0.1.0
Summary: Create .gitignore files from CLI.
Author-email: Calvin Sprouse <sprousecal@gmail.com>
Project-URL: Homepage, https://github.com/CalvinSprouse/ignorepy
Project-URL: Bug Tracker, https://github.com/CalvinSprouse/ignorepy/issues
Keywords: gitignore,.gitignore,cli,git,github
Classifier: Programming Language :: Python :: 3
Classifier: License :: OSI Approved :: MIT License
Classifier: Operating System :: OS Independent
Requires-Python: >=3.7
License-File: LICENSE
Requires-Dist: requests
Requires-Dist: rich
Requires-Dist: pyperclip
